bonnie/__init__.py
bonnie/cli.py
bonnie/definitions/__init__.py
bonnie/excel/__init__.py
bonnie/excel/actions.py
bonnie/excel/common.py
bonnie/excel/entry.py
bonnie/excel/transpose.py
bonnie/utils/__init__.py
bonnie/utils/file.py
tests/__init__.py
tests/test_file.py
bonnie_tools-0.0.3.dist-info/METADATA
bonnie_tools-0.0.3.dist-info/WHEEL
bonnie_tools-0.0.3.dist-info/entry_points.txt
bonnie_tools-0.0.3.dist-info/top_level.txt
bonnie_tools-0.0.3.dist-info/RECORD
