Metadata-Version: 2.1
Name: bonnie-tools
Version: 0.0.3
Summary: Bonnie Tools
Author: Jie Meng
Author-email: jmengxy@gmail.com
Requires-Dist: click (<9.0.0,>=8.1.3)
Requires-Dist: openpyxl (<3.2.0,>=3.1.2)
